{
  "applications": [
    {
      "appId": "Conformance1",
      "name": "Conformance1",
      "title": "FDC3 2.0 Conformance Framework",
      "description": "Testing Conformance",
      "type": "web",
      "details": {
        "url": "http://localhost:3001/v2.0/app/index.html"
      },
      "screenshots": [
        {
          "src": "https://directory.fdc3.finos.org/assets/app/Conformance1.png"
        }
      ],
      "hostManifests": {
        "sail": {
          "inject-api": "2.0"
        }
      },
      "version": "1.0.0",
      "publisher": "Scott Logic",
      "icons": [
        {
          "src": "https://www.scottlogic.com/sites/default/files/scott-logic-favicon.jpg"
        }
      ]
    },
    {
      "appId": "ChannelsAppId",
      "name": "ChannelsApp",
      "title": "Channels App",
      "description": "Part of the FDC3 2.0 Conformance Tests",
      "type": "web",
      "details": {
        "url": "http://localhost:3001/v2.0/channels"
      },
      "hostManifests": {
        "sail": {
          "inject-api": "2.0",
          "searchable": false
        }
      },
      "version": "1.0.0",
      "publisher": "Scott Logic",
      "icons": [
        {
          "src": "https://www.scottlogic.com/sites/default/files/scott-logic-favicon.jpg"
        }
      ]
    }
  ],
  "message": "OK"
}